hf_transfer-0.1.9.dist-info/METADATA
hf_transfer-0.1.9.dist-info/WHEEL
hf_transfer-0.1.9.dist-info/licenses/LICENSE
hf_transfer/__init__.py
hf_transfer/hf_transfer.cpython-313t-arm-linux-gnueabihf.so
hf_transfer-0.1.9.dist-info/RECORD
