Metadata-Version: 2.4
Name: hf_transfer
Version: 0.1.9
Classifier: Programming Language :: Rust
Classifier: Programming Language :: Python :: Implementation :: CPython
Classifier: Programming Language :: Python :: Implementation :: PyPy
License-File: LICENSE
Summary: Speed up file transfers with the Hugging Face Hub.
Requires-Python: >=3.7
Project-URL: Issues, https://github.com/huggingface/hf_transfer/issues
Project-URL: Repository, https://github.com/huggingface/hf_transfer.git
